byterec_models/__init__.py
byterec_models-0.8.3.dist-info/METADATA
byterec_models-0.8.3.dist-info/WHEEL
byterec_models-0.8.3.dist-info/top_level.txt
byterec_models-0.8.3.dist-info/RECORD
