Metadata-Version: 2.1
Name: byterec-models
Version: 0.8.3
Summary: test
Author: serverinspector2
Author-email: serverinspector+2@wearehackerone.com
Requires-Dist: requests
